odoo/addons/survey_legal/README.rst
odoo/addons/survey_legal/__init__.py
odoo/addons/survey_legal/__manifest__.py
odoo/addons/survey_legal/controllers/__init__.py
odoo/addons/survey_legal/controllers/main.py
odoo/addons/survey_legal/i18n/es.po
odoo/addons/survey_legal/i18n/it.po
odoo/addons/survey_legal/i18n/survey_legal.pot
odoo/addons/survey_legal/models/__init__.py
odoo/addons/survey_legal/models/survey.py
odoo/addons/survey_legal/models/survey_user_input.py
odoo/addons/survey_legal/readme/CONFIGURE.md
odoo/addons/survey_legal/readme/CONTRIBUTORS.md
odoo/addons/survey_legal/readme/DESCRIPTION.md
odoo/addons/survey_legal/static/description/icon.png
odoo/addons/survey_legal/static/description/index.html
odoo/addons/survey_legal/static/src/js/survey_form.esm.js
odoo/addons/survey_legal/static/tests/survey_legal_tour.esm.js
odoo/addons/survey_legal/tests/__init__.py
odoo/addons/survey_legal/tests/test_survey_legal.py
odoo/addons/survey_legal/views/survey_templates.xml
odoo/addons/survey_legal/views/survey_user_input_views.xml
odoo/addons/survey_legal/views/survey_views.xml
odoo_addon_survey_legal-17.0.1.0.0.2.dist-info/METADATA
odoo_addon_survey_legal-17.0.1.0.0.2.dist-info/WHEEL
odoo_addon_survey_legal-17.0.1.0.0.2.dist-info/top_level.txt
odoo_addon_survey_legal-17.0.1.0.0.2.dist-info/RECORD
